automic/__init__.py
automic/automaton.py
automic/torch_automaton.py
automic-0.0.3.dist-info/licenses/LICENSE
automic-0.0.3.dist-info/METADATA
automic-0.0.3.dist-info/WHEEL
automic-0.0.3.dist-info/top_level.txt
automic-0.0.3.dist-info/RECORD
