Metadata-Version: 2.4
Name: automic
Version: 0.0.3
Summary: A library for manipulating finite-state automata
Home-page: https://github.com/person594/automic
Author: Sean Papay
Author-email: sean.papay@ims.uni-stuttgart.de
Project-URL: Bug Tracker, https://github.com/person594/automic/issues
Classifier: Programming Language :: Python :: 3
Classifier: License :: OSI Approved :: MIT License
Classifier: Operating System :: OS Independent
Requires-Python: >=3.6
License-File: LICENSE
Dynamic: license-file
